freedvtnc/__main__.py
freedvtnc/freedv.py
freedvtnc/rf.py
freedvtnc/rigctl.py
freedvtnc/tnc.py
freedvtnc-0.4.0.dist-info/entry_points.txt
freedvtnc-0.4.0.dist-info/WHEEL
freedvtnc-0.4.0.dist-info/METADATA
freedvtnc-0.4.0.dist-info/RECORD
