Metadata-Version: 2.1
Name: freedvtnc
Version: 0.4.0
Summary: 
License: WTFPL
Author: xssfox
Requires-Python: >=3.6,<4.0
Classifier: License :: Other/Proprietary License
Classifier: Programming Language :: Python :: 3
Classifier: Programming Language :: Python :: 3.6
Classifier: Programming Language :: Python :: 3.7
Classifier: Programming Language :: Python :: 3.8
Classifier: Programming Language :: Python :: 3.9
Requires-Dist: kissfix (>=7.0.11,<8.0.0)
Requires-Dist: pyaudio (>=0.2.11,<0.3.0)
